id_svo_extractor/__init__.py
id_svo_extractor/pipeline.py
id_svo_extractor/svo_extractor.py
id_svo_extractor/utils.py
id_svo_extractor-0.3.0.dist-info/LICENSE
id_svo_extractor-0.3.0.dist-info/METADATA
id_svo_extractor-0.3.0.dist-info/WHEEL
id_svo_extractor-0.3.0.dist-info/top_level.txt
id_svo_extractor-0.3.0.dist-info/RECORD
