Metadata-Version: 2.1
Name: id-svo-extractor
Version: 0.3.0
Summary: id-svo-extractor: Extract SVO triples from Indonesian text.
Author-email: Nikolaus Georgi <int.nxgeo@gmail.com>
Maintainer-email: Nikolaus Georgi <int.nxgeo@gmail.com>
License: Apache License
Project-URL: Homepage, https://github.com/nxgeo/id-svo-extractor
Project-URL: Repository, https://github.com/nxgeo/id-svo-extractor.git
Keywords: SVO extraction,Indonesian NLP,Stanza,information extraction,text analysis
Classifier: Development Status :: 4 - Beta
Classifier: Intended Audience :: Developers
Classifier: Intended Audience :: Education
Classifier: Intended Audience :: Science/Research
Classifier: Topic :: Scientific/Engineering :: Artificial Intelligence
Classifier: Programming Language :: Python :: 3.10
Classifier: License :: OSI Approved :: Apache Software License
Classifier: Operating System :: OS Independent
Requires-Python: >=3.10
License-File: LICENSE
Requires-Dist: spacy-stanza ==1.0.4
